spiralarr/__init__.py
spiralarr/main.py
spiralarr-0.0.1.dist-info/METADATA
spiralarr-0.0.1.dist-info/WHEEL
spiralarr-0.0.1.dist-info/entry_points.txt
spiralarr-0.0.1.dist-info/licenses/LICENSE
spiralarr-0.0.1.dist-info/RECORD
